righty/__init__.py
righty/info.py
righty-0.1.0.dist-info/METADATA
righty-0.1.0.dist-info/WHEEL
righty-0.1.0.dist-info/top_level.txt
righty-0.1.0.dist-info/RECORD
