Metadata-Version: 2.1
Name: righty
Version: 0.1.0
Summary: Code to interact with the "righty" fly CNS GridTape-TEM dataset
Home-page: https://github.com/jasper-tms/righty
Author: Jasper Phelps
Author-email: jasper.s.phelps@gmail.com
License: UNKNOWN
Platform: UNKNOWN
Classifier: Programming Language :: Python :: 3
Classifier: Operating System :: OS Independent
Requires-Python: >=3.6
Requires-Dist: numpy
